setup.py
network_topology/__init__.py
network_topology/match.py
network_topology/topo.py
network_topology.egg-info/PKG-INFO
network_topology.egg-info/SOURCES.txt
network_topology.egg-info/dependency_links.txt
network_topology.egg-info/not-zip-safe
network_topology.egg-info/requires.txt
network_topology.egg-info/top_level.txt