Metadata-Version: 1.0
Name: network-topology
Version: 0.2.1
Summary: Simplify overlapping lines into a single graph
Home-page: http://github.com/TriTAG/network-topology
Author: Mike Boos
Author-email: mike.boos@tritag.ca
License: BSD
Platform: UNKNOWN
